MANIFEST.in
README.txt
setup.cfg
setup.py
plonetheme/__init__.py
plonetheme.andreas02.egg-info/PKG-INFO
plonetheme.andreas02.egg-info/SOURCES.txt
plonetheme.andreas02.egg-info/dependency_links.txt
plonetheme.andreas02.egg-info/entry_points.txt
plonetheme.andreas02.egg-info/namespace_packages.txt
plonetheme.andreas02.egg-info/not-zip-safe
plonetheme.andreas02.egg-info/paster_plugins.txt
plonetheme.andreas02.egg-info/requires.txt
plonetheme.andreas02.egg-info/top_level.txt
plonetheme/andreas02/__init__.py
plonetheme/andreas02/configure.zcml
plonetheme/andreas02/profiles.zcml
plonetheme/andreas02/setuphandlers.py
plonetheme/andreas02/skins.zcml
plonetheme/andreas02/tests.py
plonetheme/andreas02/version.txt
plonetheme/andreas02/browser/__init__.py
plonetheme/andreas02/browser/configure.zcml
plonetheme/andreas02/browser/footer.pt
plonetheme/andreas02/browser/interfaces.py
plonetheme/andreas02/browser/splash_image.pt
plonetheme/andreas02/browser/viewlet.pt
plonetheme/andreas02/browser/viewlets.py
plonetheme/andreas02/browser/images/README.txt
plonetheme/andreas02/browser/stylesheets/README.txt
plonetheme/andreas02/browser/stylesheets/main.css
plonetheme/andreas02/profiles/default/cssregistry.xml
plonetheme/andreas02/profiles/default/import_steps.xml
plonetheme/andreas02/profiles/default/jsregistry.xml
plonetheme/andreas02/profiles/default/metadata.xml
plonetheme/andreas02/profiles/default/old_portlets.xml
plonetheme/andreas02/profiles/default/plonetheme.andreas02_various.txt
plonetheme/andreas02/profiles/default/skins.xml
plonetheme/andreas02/profiles/default/viewlets.xml
plonetheme/andreas02/skins/plonetheme_andreas02_custom_images/CONTENT.txt
plonetheme/andreas02/skins/plonetheme_andreas02_custom_images/banner.jpg
plonetheme/andreas02/skins/plonetheme_andreas02_custom_images/corner.gif
plonetheme/andreas02/skins/plonetheme_andreas02_custom_images/corner2.gif
plonetheme/andreas02/skins/plonetheme_andreas02_custom_templates/CONTENT.txt
plonetheme/andreas02/skins/plonetheme_andreas02_custom_templates/main_template.pt
plonetheme/andreas02/skins/plonetheme_andreas02_styles/CONTENT.txt
plonetheme/andreas02/skins/plonetheme_andreas02_styles/IEFixes.css.dtml
plonetheme/andreas02/skins/plonetheme_andreas02_styles/andreas02.css.dtml
plonetheme/andreas02/skins/plonetheme_andreas02_styles/base.css.dtml
plonetheme/andreas02/skins/plonetheme_andreas02_styles/base_properties.props
