Metadata-Version: 1.0
Name: plonetheme.andreas02
Version: 0.2
Summary: An installable theme for Plone 3.0
Home-page: http://svn.plone.org/svn/collective/
Author: David Little
Author-email: david@littled.net
License: GPL
Keywords: web zope plone theme
Platform: UNKNOWN
Classifier: Framework :: Plone
Classifier: Programming Language :: Python
Classifier: Topic :: Software Development :: Libraries :: Python Modules
